{
  "artist": "Nessa Barrett",
  "album": "AFTERCARE",
  "status": "musicbrainz",
  "tracks": [
    {
      "number": 1,
      "title": "AFTERCARE",
      "durationMs": 93947
    },
    {
      "number": 2,
      "title": "P*RNSTAR",
      "durationMs": 149440
    },
    {
      "number": 3,
      "title": "HEARTBEAT",
      "durationMs": 189293
    },
    {
      "number": 4,
      "title": "DISCO",
      "durationMs": 197587
    },
    {
      "number": 5,
      "title": "PASSENGER PRINCESS",
      "durationMs": 155578
    },
    {
      "number": 6,
      "title": "MUSTANG BABY",
      "durationMs": 191680
    },
    {
      "number": 7,
      "title": "RUSSIAN ROULETTE",
      "durationMs": 160360
    },
    {
      "number": 8,
      "title": "S.L.U.T.",
      "durationMs": 148467
    },
    {
      "number": 9,
      "title": "BABYDOLL",
      "durationMs": 219000
    },
    {
      "number": 10,
      "title": "GIVEN ENOUGH",
      "durationMs": 204480
    },
    {
      "number": 11,
      "title": "EDWARD SCISSORHANDS",
      "durationMs": 211147
    },
    {
      "number": 12,
      "title": "GLITTER AND VIOLENCE",
      "durationMs": 184933
    },
    {
      "number": 13,
      "title": "PINS AND NEEDLES",
      "durationMs": 201747
    },
    {
      "number": 14,
      "title": "STAY ALIVE",
      "durationMs": 190893
    },
    {
      "number": 15,
      "title": "DIRTY LITTLE SECRET",
      "durationMs": 214840
    }
  ],
  "albumDurationMs": 2713392,
  "year": 2024,
  "trackCount": 15,
  "musicbrainzReleaseGroupId": "7f40718f-2b31-4d9b-88a7-b7f49cb8a330"
}
