{
  "artist": "MGMT",
  "album": "Oracular Spectacular",
  "year": 2007,
  "releaseDate": "2007-10-02T07:00:00Z",
  "genre": "Alternative",
  "trackCount": 10,
  "artworkUrl": "https://is1-ssl.mzstatic.com/image/thumb/Music115/v4/e5/06/cc/e506ccd5-56ec-3d4c-69f7-14900bea74f0/mzi.bbgsikee.jpg/600x600bb.jpg",
  "artistUrl": "https://music.apple.com/us/artist/mgmt/251553551?uo=4",
  "albumUrl": "https://music.apple.com/us/album/oracular-spectacular/273519664?uo=4",
  "status": "musicbrainz",
  "tracks": [
    {
      "number": 1,
      "title": "Time to Pretend",
      "durationMs": 261000
    },
    {
      "number": 2,
      "title": "Weekend Wars",
      "durationMs": 250773
    },
    {
      "number": 3,
      "title": "The Youth",
      "durationMs": 228013
    },
    {
      "number": 4,
      "title": "Electric Feel",
      "durationMs": 229640
    },
    {
      "number": 5,
      "title": "Kids",
      "durationMs": 302840
    },
    {
      "number": 6,
      "title": "4th Dimensional Transition",
      "durationMs": 238013
    },
    {
      "number": 7,
      "title": "Pieces of What",
      "durationMs": 163773
    },
    {
      "number": 8,
      "title": "Of Moons, Birds & Monsters",
      "durationMs": 286720
    },
    {
      "number": 9,
      "title": "The Handshake",
      "durationMs": 219627
    },
    {
      "number": 10,
      "title": "Future Reflections",
      "durationMs": 240253
    }
  ],
  "albumDurationMs": 2420652,
  "musicbrainzReleaseGroupId": "f7da2770-bf72-3dea-8904-ff6135822724"
}
